Metadata-Version: 2.1
Name: checksum-calculator
Version: 1.0.0
Summary: Simple checksum calculator
Home-page: https://gitlab.com/olive007/checksum-calculator
Author: SECRET Olivier
Author-email: pypi-package-checksum_calculator@devo.live
License: UNKNOWN
Platform: UNKNOWN
Classifier: Programming Language :: Python :: 3
Classifier: License :: OSI Approved :: GNU Lesser General Public License v3 or later (LGPLv3+)
Classifier: Operating System :: OS Independent
License-File: LICENSE
